{"timestamp":0,"files":[{"path":"C:/Users/wb198/Desktop/My project/TextToolDatas\\slim\\backup.txt","dstPath":null,"md5":"2cbfd26902dd9d06","textures":[{"width":64,"height":8,"name":"Invalidated.1f296ba4","astc":null,"limittype":null},{"width":32,"height":32,"name":"UISprite.b48f75d0","astc":null,"limittype":null},{"width":32,"height":32,"name":"Background.665e03a7","astc":null,"limittype":null},{"width":64,"height":64,"name":"Knob.dadd3d45","astc":null,"limittype":null},{"width":1152,"height":2048,"name":"1.7a45c63d","astc":null,"limittype":null},{"width":100,"height":100,"name":"%E9%87%91%E5%B8%81.a276305f","astc":null,"limittype":null},{"width":100,"height":100,"name":"%E7%AE%A1%E7%90%86.9db073ab","astc":null,"limittype":null},{"width":100,"height":100,"name":"%E9%92%BB%E7%9F%B3.bf50840a","astc":null,"limittype":null},{"width":100,"height":100,"name":"%E6%97%A5%E5%8E%86.bf78564b","astc":null,"limittype":null},{"width":100,"height":100,"name":"%E5%8D%96%E5%AE%B6%E5%BA%97%E9%93%BA.32707a1f","astc":null,"limittype":null},{"width":100,"height":100,"name":"%E5%95%86%E4%B8%9A%E5%8C%96%E5%85%A8%E7%90%83.c83bd0dd","astc":null,"limittype":null},{"width":100,"height":100,"name":"%E7%94%A8%E6%88%B7.8ab9eb89","astc":null,"limittype":null},{"width":100,"height":100,"name":"%E4%BD%93%E5%8A%9B.c93105fc","astc":null,"limittype":null},{"width":100,"height":100,"name":"2.ce01e079","astc":null,"limittype":null},{"width":100,"height":100,"name":"3.f01445bd","astc":null,"limittype":null},{"width":400,"height":100,"name":"Sprite-0001%201.b07db787","astc":null,"limittype":null},{"width":1152,"height":2048,"name":"2.899fd39e","astc":null,"limittype":null},{"width":107,"height":100,"name":"%E5%83%8F%E7%B4%A0-%E8%93%9D%E8%98%91%E8%8F%87.4f42af72","astc":null,"limittype":"1"},{"width":400,"height":100,"name":"Sprite-0001.800a9893","astc":null,"limittype":null},{"width":1024,"height":1024,"name":"%E5%9D%90%E6%A0%87.f2407314","astc":null,"limittype":null},{"width":107,"height":100,"name":"%E5%83%8F%E7%B4%A0-%E7%BA%A2%E8%98%91%E8%8F%87.ef5185a2","astc":null,"limittype":"1"},{"width":107,"height":100,"name":"%E5%83%8F%E7%B4%A0-%E7%BB%BF%E8%98%91%E8%8F%87.dc157c31","astc":null,"limittype":"1"},{"width":100,"height":100,"name":"%E7%88%B1%E5%BF%83.797b9614","astc":null,"limittype":null},{"width":100,"height":100,"name":"1.d3abb9a9","astc":null,"limittype":null},{"width":100,"height":100,"name":"%E7%9C%BC%E7%9D%9B.3c0e84be","astc":null,"limittype":null},{"width":100,"height":100,"name":"%E9%98%B2%E5%BE%A1%E5%A1%94.65bd325e","astc":null,"limittype":null},{"width":100,"height":100,"name":"%E5%9C%86%E5%9E%8B-%E5%8D%95%E9%80%89%E6%A1%86-%E7%A6%81%E7%94%A8-%E6%9C%AA%E9%80%89.4053f64a","astc":null,"limittype":null},{"width":512,"height":512,"name":"EmojiOne.9438d40e","astc":null,"limittype":null},{"width":1024,"height":1024,"name":"LiberationSans%20SDF%20Atlas.ac9f1c83","astc":null,"limittype":null}]}]}